moya/__init__.py
moya/agents/__init__.py
moya/agents/agent_info.py
moya/agents/azure_openai_agent.py
moya/agents/base_agent.py
moya/agents/bedrock_agent.py
moya/agents/crewai_agent.py
moya/agents/ollama_agent.py
moya/agents/openai_agent.py
moya/agents/remote_agent.py
moya/classifiers/base_classifier.py
moya/classifiers/llm_classifier.py
moya/conversation/__init__.py
moya/conversation/message.py
moya/conversation/thread.py
moya/memory/__init__.py
moya/memory/base_repository.py
moya/memory/file_system_repo.py
moya/memory/in_memory_repository.py
moya/orchestrators/__init__.py
moya/orchestrators/base_orchestrator.py
moya/orchestrators/multi_agent_orchestrator.py
moya/orchestrators/react_orchestrator.py
moya/orchestrators/simple_orchestrator.py
moya/registry/__init__.py
moya/registry/agent_registry.py
moya/registry/base_agent_repository.py
moya/registry/in_memory_agent_repository.py
moya/tools/__init__.py
moya/tools/base_tool.py
moya/tools/ephemeral_memory.py
moya/tools/tool_registry.py
moya/utils/constants.py
moya_ai-0.1.4.dist-info/LICENSE
moya_ai-0.1.4.dist-info/METADATA
moya_ai-0.1.4.dist-info/WHEEL
moya_ai-0.1.4.dist-info/top_level.txt
moya_ai-0.1.4.dist-info/RECORD
