Metadata-Version: 2.2
Name: moya-ai
Version: 0.1.4
Summary: A reference implementation of the Moya AI framework.
Author-email: MontyCloud <kannan@montycloud.com>
License: MIT License
Keywords: python,moya
Classifier: Development Status :: 3 - Alpha
Classifier: Programming Language :: Python :: 3
Classifier: License :: OSI Approved :: MIT License
Classifier: Operating System :: OS Independent
Requires-Python: >=3.11
License-File: LICENSE
Requires-Dist: boto3>=1.36.9
Requires-Dist: crewai>=0.100.1
Requires-Dist: crewai-tools>=0.33.0
Requires-Dist: requests>=2.32.3
Requires-Dist: openai>=1.60.1
Requires-Dist: fastapi>=0.115.7
Requires-Dist: uvicorn>=0.34.0
Requires-Dist: dotenv>=1.0.1
